{
  "tafsir": {
    "37_103": {
      "text": "فَلَمَّا أَسْلَمَا وَتَلَّهُ لِلْجَبِينِ"
    },
    "37_104": {
      "text": "وَنَادَيْنَاهُ أَن يَا إِبْرَاهِيمُ"
    },
    "37_105": {
      "text": "قَدْ صَدَّقْتَ الرُّؤْيَا ۚ إِنَّا كَذَٰلِكَ نَجْزِي الْمُحْسِنِينَ"
    },
    "37_106": {
      "text": "إِنَّ هَٰذَا لَهُوَ الْبَلَاءُ الْمُبِينُ"
    },
    "37_107": {
      "text": "وَفَدَيْنَاهُ بِذِبْحٍ عَظِيمٍ"
    },
    "37_108": {
      "text": "وَتَرَكْنَا عَلَيْهِ فِي الْآخِرِينَ"
    },
    "37_109": {
      "text": "سَلَامٌ عَلَىٰ إِبْرَاهِيمَ"
    },
    "37_110": {
      "text": "كَذَٰلِكَ نَجْزِي الْمُحْسِنِينَ"
    },
    "37_111": {
      "text": "إِنَّهُ مِنْ عِبَادِنَا الْمُؤْمِنِينَ"
    },
    "37_112": {
      "text": "وَبَشَّرْنَاهُ بِإِسْحَاقَ نَبِيًّا مِّنَ الصَّالِحِينَ"
    },
    "37_113": {
      "text": "وَبَارَكْنَا عَلَيْهِ وَعَلَىٰ إِسْحَاقَ ۚ وَمِن ذُرِّيَّتِهِمَا مُحْسِنٌ وَظَالِمٌ لِّنَفْسِهِ مُبِينٌ"
    },
    "37_114": {
      "text": "وَلَقَدْ مَنَنَّا عَلَىٰ مُوسَىٰ وَهَارُونَ"
    },
    "37_115": {
      "text": "وَنَجَّيْنَاهُمَا وَقَوْمَهُمَا مِنَ الْكَرْبِ الْعَظِيمِ"
    },
    "37_116": {
      "text": "وَنَصَرْنَاهُمْ فَكَانُوا هُمُ الْغَالِبِينَ"
    },
    "37_117": {
      "text": "وَآتَيْنَاهُمَا الْكِتَابَ الْمُسْتَبِينَ"
    },
    "37_118": {
      "text": "وَهَدَيْنَاهُمَا الصِّرَاطَ الْمُسْتَقِيمَ"
    },
    "37_119": {
      "text": "وَتَرَكْنَا عَلَيْهِمَا فِي الْآخِرِينَ"
    },
    "37_120": {
      "text": "سَلَامٌ عَلَىٰ مُوسَىٰ وَهَارُونَ"
    },
    "37_121": {
      "text": "إِنَّا كَذَٰلِكَ نَجْزِي الْمُحْسِنِينَ"
    },
    "37_122": {
      "text": "إِنَّهُمَا مِنْ عِبَادِنَا الْمُؤْمِنِينَ"
    },
    "37_123": {
      "text": "وَإِنَّ إِلْيَاسَ لَمِنَ الْمُرْسَلِينَ"
    },
    "37_124": {
      "text": "إِذْ قَالَ لِقَوْمِهِ أَلَا تَتَّقُونَ"
    },
    "37_125": {
      "text": "أَتَدْعُونَ بَعْلًا وَتَذَرُونَ أَحْسَنَ الْخَالِقِينَ"
    },
    "37_126": {
      "text": "اللَّهَ رَبَّكُمْ وَرَبَّ آبَائِكُمُ الْأَوَّلِينَ"
    }
  }
}